[
    {
        "username": "afrozenator",
        "id": 1131030,
        "followers_url": "https://api.github.com/users/afrozenator/followers",
        "repositories_url": "https://api.github.com/users/afrozenator/repos",
        "star_url": "https://api.github.com/users/afrozenator/starred{/owner}{/repo}",
        "contributions": 359
    },
    {
        "username": "lukaszkaiser",
        "id": 684901,
        "followers_url": "https://api.github.com/users/lukaszkaiser/followers",
        "repositories_url": "https://api.github.com/users/lukaszkaiser/repos",
        "star_url": "https://api.github.com/users/lukaszkaiser/starred{/owner}{/repo}",
        "contributions": 214
    },
    {
        "username": "koz4k",
        "id": 1211366,
        "followers_url": "https://api.github.com/users/koz4k/followers",
        "repositories_url": "https://api.github.com/users/koz4k/repos",
        "star_url": "https://api.github.com/users/koz4k/starred{/owner}{/repo}",
        "contributions": 182
    },
    {
        "username": "nshazeer",
        "id": 29785582,
        "followers_url": "https://api.github.com/users/nshazeer/followers",
        "repositories_url": "https://api.github.com/users/nshazeer/repos",
        "star_url": "https://api.github.com/users/nshazeer/starred{/owner}{/repo}",
        "contributions": 166
    },
    {
        "username": "mbz",
        "id": 1122127,
        "followers_url": "https://api.github.com/users/mbz/followers",
        "repositories_url": "https://api.github.com/users/mbz/repos",
        "star_url": "https://api.github.com/users/mbz/starred{/owner}{/repo}",
        "contributions": 143
    },
    {
        "username": "dustinvtran",
        "id": 2569867,
        "followers_url": "https://api.github.com/users/dustinvtran/followers",
        "repositories_url": "https://api.github.com/users/dustinvtran/repos",
        "star_url": "https://api.github.com/users/dustinvtran/starred{/owner}{/repo}",
        "contributions": 113
    },
    {
        "username": "MechCoder",
        "id": 1867024,
        "followers_url": "https://api.github.com/users/MechCoder/followers",
        "repositories_url": "https://api.github.com/users/MechCoder/repos",
        "star_url": "https://api.github.com/users/MechCoder/starred{/owner}{/repo}",
        "contributions": 89
    },
    {
        "username": "vthorsteinsson",
        "id": 8191848,
        "followers_url": "https://api.github.com/users/vthorsteinsson/followers",
        "repositories_url": "https://api.github.com/users/vthorsteinsson/repos",
        "star_url": "https://api.github.com/users/vthorsteinsson/starred{/owner}{/repo}",
        "contributions": 74
    },
    {
        "username": "urvashik",
        "id": 3162683,
        "followers_url": "https://api.github.com/users/urvashik/followers",
        "repositories_url": "https://api.github.com/users/urvashik/repos",
        "star_url": "https://api.github.com/users/urvashik/starred{/owner}{/repo}",
        "contributions": 52
    },
    {
        "username": "blazejosinski",
        "id": 804945,
        "followers_url": "https://api.github.com/users/blazejosinski/followers",
        "repositories_url": "https://api.github.com/users/blazejosinski/repos",
        "star_url": "https://api.github.com/users/blazejosinski/starred{/owner}{/repo}",
        "contributions": 51
    },
    {
        "username": "konradczechowski",
        "id": 5443665,
        "followers_url": "https://api.github.com/users/konradczechowski/followers",
        "repositories_url": "https://api.github.com/users/konradczechowski/repos",
        "star_url": "https://api.github.com/users/konradczechowski/starred{/owner}{/repo}",
        "contributions": 49
    },
    {
        "username": "royaurko",
        "id": 8907160,
        "followers_url": "https://api.github.com/users/royaurko/followers",
        "repositories_url": "https://api.github.com/users/royaurko/repos",
        "star_url": "https://api.github.com/users/royaurko/starred{/owner}{/repo}",
        "contributions": 47
    },
    {
        "username": "lgeiger",
        "id": 13285808,
        "followers_url": "https://api.github.com/users/lgeiger/followers",
        "repositories_url": "https://api.github.com/users/lgeiger/repos",
        "star_url": "https://api.github.com/users/lgeiger/starred{/owner}{/repo}",
        "contributions": 37
    },
    {
        "username": "stefan-it",
        "id": 20651387,
        "followers_url": "https://api.github.com/users/stefan-it/followers",
        "repositories_url": "https://api.github.com/users/stefan-it/repos",
        "star_url": "https://api.github.com/users/stefan-it/starred{/owner}{/repo}",
        "contributions": 36
    },
    {
        "username": "martinpopel",
        "id": 724617,
        "followers_url": "https://api.github.com/users/martinpopel/followers",
        "repositories_url": "https://api.github.com/users/martinpopel/repos",
        "star_url": "https://api.github.com/users/martinpopel/starred{/owner}{/repo}",
        "contributions": 33
    },
    {
        "username": "Conchylicultor",
        "id": 9047355,
        "followers_url": "https://api.github.com/users/Conchylicultor/followers",
        "repositories_url": "https://api.github.com/users/Conchylicultor/repos",
        "star_url": "https://api.github.com/users/Conchylicultor/starred{/owner}{/repo}",
        "contributions": 32
    },
    {
        "username": "aidangomez",
        "id": 9597721,
        "followers_url": "https://api.github.com/users/aidangomez/followers",
        "repositories_url": "https://api.github.com/users/aidangomez/repos",
        "star_url": "https://api.github.com/users/aidangomez/starred{/owner}{/repo}",
        "contributions": 30
    },
    {
        "username": "lmthang",
        "id": 396613,
        "followers_url": "https://api.github.com/users/lmthang/followers",
        "repositories_url": "https://api.github.com/users/lmthang/repos",
        "star_url": "https://api.github.com/users/lmthang/starred{/owner}{/repo}",
        "contributions": 15
    },
    {
        "username": "kolloldas",
        "id": 20799906,
        "followers_url": "https://api.github.com/users/kolloldas/followers",
        "repositories_url": "https://api.github.com/users/kolloldas/repos",
        "star_url": "https://api.github.com/users/kolloldas/starred{/owner}{/repo}",
        "contributions": 13
    },
    {
        "username": "ReDeiPirati",
        "id": 5721767,
        "followers_url": "https://api.github.com/users/ReDeiPirati/followers",
        "repositories_url": "https://api.github.com/users/ReDeiPirati/repos",
        "star_url": "https://api.github.com/users/ReDeiPirati/starred{/owner}{/repo}",
        "contributions": 13
    },
    {
        "username": "wangpengmit",
        "id": 7817365,
        "followers_url": "https://api.github.com/users/wangpengmit/followers",
        "repositories_url": "https://api.github.com/users/wangpengmit/repos",
        "star_url": "https://api.github.com/users/wangpengmit/starred{/owner}{/repo}",
        "contributions": 12
    },
    {
        "username": "dusenberrymw",
        "id": 5431337,
        "followers_url": "https://api.github.com/users/dusenberrymw/followers",
        "repositories_url": "https://api.github.com/users/dusenberrymw/repos",
        "star_url": "https://api.github.com/users/dusenberrymw/starred{/owner}{/repo}",
        "contributions": 11
    },
    {
        "username": "EndingCredits",
        "id": 9828880,
        "followers_url": "https://api.github.com/users/EndingCredits/followers",
        "repositories_url": "https://api.github.com/users/EndingCredits/repos",
        "star_url": "https://api.github.com/users/EndingCredits/starred{/owner}{/repo}",
        "contributions": 11
    },
    {
        "username": "toponado-zz",
        "id": 2306823,
        "followers_url": "https://api.github.com/users/toponado-zz/followers",
        "repositories_url": "https://api.github.com/users/toponado-zz/repos",
        "star_url": "https://api.github.com/users/toponado-zz/starred{/owner}{/repo}",
        "contributions": 10
    },
    {
        "username": "artitw",
        "id": 20779121,
        "followers_url": "https://api.github.com/users/artitw/followers",
        "repositories_url": "https://api.github.com/users/artitw/repos",
        "star_url": "https://api.github.com/users/artitw/starred{/owner}{/repo}",
        "contributions": 10
    },
    {
        "username": "stefan-falk",
        "id": 43335432,
        "followers_url": "https://api.github.com/users/stefan-falk/followers",
        "repositories_url": "https://api.github.com/users/stefan-falk/repos",
        "star_url": "https://api.github.com/users/stefan-falk/starred{/owner}{/repo}",
        "contributions": 9
    },
    {
        "username": "cbockman",
        "id": 4667922,
        "followers_url": "https://api.github.com/users/cbockman/followers",
        "repositories_url": "https://api.github.com/users/cbockman/repos",
        "star_url": "https://api.github.com/users/cbockman/starred{/owner}{/repo}",
        "contributions": 9
    },
    {
        "username": "ziy",
        "id": 2071996,
        "followers_url": "https://api.github.com/users/ziy/followers",
        "repositories_url": "https://api.github.com/users/ziy/repos",
        "star_url": "https://api.github.com/users/ziy/starred{/owner}{/repo}",
        "contributions": 9
    },
    {
        "username": "katelee168",
        "id": 6434764,
        "followers_url": "https://api.github.com/users/katelee168/followers",
        "repositories_url": "https://api.github.com/users/katelee168/repos",
        "star_url": "https://api.github.com/users/katelee168/starred{/owner}{/repo}",
        "contributions": 9
    },
    {
        "username": "keyonvafa",
        "id": 10766891,
        "followers_url": "https://api.github.com/users/keyonvafa/followers",
        "repositories_url": "https://api.github.com/users/keyonvafa/repos",
        "star_url": "https://api.github.com/users/keyonvafa/starred{/owner}{/repo}",
        "contributions": 9
    },
    {
        "username": "vince62s",
        "id": 15141326,
        "followers_url": "https://api.github.com/users/vince62s/followers",
        "repositories_url": "https://api.github.com/users/vince62s/repos",
        "star_url": "https://api.github.com/users/vince62s/starred{/owner}{/repo}",
        "contributions": 8
    },
    {
        "username": "brian-barnes",
        "id": 39046298,
        "followers_url": "https://api.github.com/users/brian-barnes/followers",
        "repositories_url": "https://api.github.com/users/brian-barnes/repos",
        "star_url": "https://api.github.com/users/brian-barnes/starred{/owner}{/repo}",
        "contributions": 7
    },
    {
        "username": "eli7",
        "id": 1028593,
        "followers_url": "https://api.github.com/users/eli7/followers",
        "repositories_url": "https://api.github.com/users/eli7/repos",
        "star_url": "https://api.github.com/users/eli7/starred{/owner}{/repo}",
        "contributions": 7
    },
    {
        "username": "dmrd",
        "id": 1198725,
        "followers_url": "https://api.github.com/users/dmrd/followers",
        "repositories_url": "https://api.github.com/users/dmrd/repos",
        "star_url": "https://api.github.com/users/dmrd/starred{/owner}{/repo}",
        "contributions": 7
    },
    {
        "username": "rshin",
        "id": 13770,
        "followers_url": "https://api.github.com/users/rshin/followers",
        "repositories_url": "https://api.github.com/users/rshin/repos",
        "star_url": "https://api.github.com/users/rshin/starred{/owner}{/repo}",
        "contributions": 7
    },
    {
        "username": "rohan100jain",
        "id": 144114,
        "followers_url": "https://api.github.com/users/rohan100jain/followers",
        "repositories_url": "https://api.github.com/users/rohan100jain/repos",
        "star_url": "https://api.github.com/users/rohan100jain/starred{/owner}{/repo}",
        "contributions": 7
    },
    {
        "username": "wingsbr",
        "id": 11762539,
        "followers_url": "https://api.github.com/users/wingsbr/followers",
        "repositories_url": "https://api.github.com/users/wingsbr/repos",
        "star_url": "https://api.github.com/users/wingsbr/starred{/owner}{/repo}",
        "contributions": 6
    },
    {
        "username": "tlatkowski",
        "id": 13836101,
        "followers_url": "https://api.github.com/users/tlatkowski/followers",
        "repositories_url": "https://api.github.com/users/tlatkowski/repos",
        "star_url": "https://api.github.com/users/tlatkowski/starred{/owner}{/repo}",
        "contributions": 6
    },
    {
        "username": "cclauss",
        "id": 3709715,
        "followers_url": "https://api.github.com/users/cclauss/followers",
        "repositories_url": "https://api.github.com/users/cclauss/repos",
        "star_url": "https://api.github.com/users/cclauss/starred{/owner}{/repo}",
        "contributions": 6
    },
    {
        "username": "yuwen-yan",
        "id": 525266,
        "followers_url": "https://api.github.com/users/yuwen-yan/followers",
        "repositories_url": "https://api.github.com/users/yuwen-yan/repos",
        "star_url": "https://api.github.com/users/yuwen-yan/starred{/owner}{/repo}",
        "contributions": 6
    },
    {
        "username": "ywkim",
        "id": 588581,
        "followers_url": "https://api.github.com/users/ywkim/followers",
        "repositories_url": "https://api.github.com/users/ywkim/repos",
        "star_url": "https://api.github.com/users/ywkim/starred{/owner}{/repo}",
        "contributions": 6
    },
    {
        "username": "Separius",
        "id": 519177,
        "followers_url": "https://api.github.com/users/Separius/followers",
        "repositories_url": "https://api.github.com/users/Separius/repos",
        "star_url": "https://api.github.com/users/Separius/starred{/owner}{/repo}",
        "contributions": 6
    },
    {
        "username": "MostafaDehghani",
        "id": 8384656,
        "followers_url": "https://api.github.com/users/MostafaDehghani/followers",
        "repositories_url": "https://api.github.com/users/MostafaDehghani/repos",
        "star_url": "https://api.github.com/users/MostafaDehghani/starred{/owner}{/repo}",
        "contributions": 6
    },
    {
        "username": "hertschuh",
        "id": 1091026,
        "followers_url": "https://api.github.com/users/hertschuh/followers",
        "repositories_url": "https://api.github.com/users/hertschuh/repos",
        "star_url": "https://api.github.com/users/hertschuh/starred{/owner}{/repo}",
        "contributions": 6
    },
    {
        "username": "doomie",
        "id": 177628,
        "followers_url": "https://api.github.com/users/doomie/followers",
        "repositories_url": "https://api.github.com/users/doomie/repos",
        "star_url": "https://api.github.com/users/doomie/starred{/owner}{/repo}",
        "contributions": 6
    },
    {
        "username": "jackd",
        "id": 659115,
        "followers_url": "https://api.github.com/users/jackd/followers",
        "repositories_url": "https://api.github.com/users/jackd/repos",
        "star_url": "https://api.github.com/users/jackd/starred{/owner}{/repo}",
        "contributions": 6
    },
    {
        "username": "aeloyq",
        "id": 20637250,
        "followers_url": "https://api.github.com/users/aeloyq/followers",
        "repositories_url": "https://api.github.com/users/aeloyq/repos",
        "star_url": "https://api.github.com/users/aeloyq/starred{/owner}{/repo}",
        "contributions": 6
    },
    {
        "username": "alexyku",
        "id": 15058050,
        "followers_url": "https://api.github.com/users/alexyku/followers",
        "repositories_url": "https://api.github.com/users/alexyku/repos",
        "star_url": "https://api.github.com/users/alexyku/starred{/owner}{/repo}",
        "contributions": 6
    },
    {
        "username": "EmilsOzolins",
        "id": 16975996,
        "followers_url": "https://api.github.com/users/EmilsOzolins/followers",
        "repositories_url": "https://api.github.com/users/EmilsOzolins/repos",
        "star_url": "https://api.github.com/users/EmilsOzolins/starred{/owner}{/repo}",
        "contributions": 5
    },
    {
        "username": "cyfra",
        "id": 11492046,
        "followers_url": "https://api.github.com/users/cyfra/followers",
        "repositories_url": "https://api.github.com/users/cyfra/repos",
        "star_url": "https://api.github.com/users/cyfra/starred{/owner}{/repo}",
        "contributions": 5
    },
    {
        "username": "pltrdy",
        "id": 6375843,
        "followers_url": "https://api.github.com/users/pltrdy/followers",
        "repositories_url": "https://api.github.com/users/pltrdy/repos",
        "star_url": "https://api.github.com/users/pltrdy/starred{/owner}{/repo}",
        "contributions": 5
    },
    {
        "username": "hawkinsp",
        "id": 348932,
        "followers_url": "https://api.github.com/users/hawkinsp/followers",
        "repositories_url": "https://api.github.com/users/hawkinsp/repos",
        "star_url": "https://api.github.com/users/hawkinsp/starred{/owner}{/repo}",
        "contributions": 5
    },
    {
        "username": "rryan",
        "id": 26527,
        "followers_url": "https://api.github.com/users/rryan/followers",
        "repositories_url": "https://api.github.com/users/rryan/repos",
        "star_url": "https://api.github.com/users/rryan/starred{/owner}{/repo}",
        "contributions": 4
    },
    {
        "username": "yynil",
        "id": 3609719,
        "followers_url": "https://api.github.com/users/yynil/followers",
        "repositories_url": "https://api.github.com/users/yynil/repos",
        "star_url": "https://api.github.com/users/yynil/starred{/owner}{/repo}",
        "contributions": 4
    },
    {
        "username": "hbrylkowski",
        "id": 5520634,
        "followers_url": "https://api.github.com/users/hbrylkowski/followers",
        "repositories_url": "https://api.github.com/users/hbrylkowski/repos",
        "star_url": "https://api.github.com/users/hbrylkowski/starred{/owner}{/repo}",
        "contributions": 4
    },
    {
        "username": "etragas-fathom",
        "id": 43351375,
        "followers_url": "https://api.github.com/users/etragas-fathom/followers",
        "repositories_url": "https://api.github.com/users/etragas-fathom/repos",
        "star_url": "https://api.github.com/users/etragas-fathom/starred{/owner}{/repo}",
        "contributions": 4
    },
    {
        "username": "Blazej0",
        "id": 98414139,
        "followers_url": "https://api.github.com/users/Blazej0/followers",
        "repositories_url": "https://api.github.com/users/Blazej0/repos",
        "star_url": "https://api.github.com/users/Blazej0/starred{/owner}{/repo}",
        "contributions": 4
    },
    {
        "username": "sun51",
        "id": 3901200,
        "followers_url": "https://api.github.com/users/sun51/followers",
        "repositories_url": "https://api.github.com/users/sun51/repos",
        "star_url": "https://api.github.com/users/sun51/starred{/owner}{/repo}",
        "contributions": 4
    },
    {
        "username": "vinhngx",
        "id": 7205508,
        "followers_url": "https://api.github.com/users/vinhngx/followers",
        "repositories_url": "https://api.github.com/users/vinhngx/repos",
        "star_url": "https://api.github.com/users/vinhngx/starred{/owner}{/repo}",
        "contributions": 4
    },
    {
        "username": "senarvi",
        "id": 2337787,
        "followers_url": "https://api.github.com/users/senarvi/followers",
        "repositories_url": "https://api.github.com/users/senarvi/repos",
        "star_url": "https://api.github.com/users/senarvi/starred{/owner}{/repo}",
        "contributions": 4
    },
    {
        "username": "rllin-fathom",
        "id": 25942131,
        "followers_url": "https://api.github.com/users/rllin-fathom/followers",
        "repositories_url": "https://api.github.com/users/rllin-fathom/repos",
        "star_url": "https://api.github.com/users/rllin-fathom/starred{/owner}{/repo}",
        "contributions": 4
    },
    {
        "username": "mikeymezher",
        "id": 5401052,
        "followers_url": "https://api.github.com/users/mikeymezher/followers",
        "repositories_url": "https://api.github.com/users/mikeymezher/repos",
        "star_url": "https://api.github.com/users/mikeymezher/starred{/owner}{/repo}",
        "contributions": 4
    },
    {
        "username": "gcampax",
        "id": 876889,
        "followers_url": "https://api.github.com/users/gcampax/followers",
        "repositories_url": "https://api.github.com/users/gcampax/repos",
        "star_url": "https://api.github.com/users/gcampax/starred{/owner}{/repo}",
        "contributions": 4
    },
    {
        "username": "EugKar",
        "id": 6560362,
        "followers_url": "https://api.github.com/users/EugKar/followers",
        "repositories_url": "https://api.github.com/users/EugKar/repos",
        "star_url": "https://api.github.com/users/EugKar/starred{/owner}{/repo}",
        "contributions": 4
    },
    {
        "username": "Vooblin",
        "id": 39566915,
        "followers_url": "https://api.github.com/users/Vooblin/followers",
        "repositories_url": "https://api.github.com/users/Vooblin/repos",
        "star_url": "https://api.github.com/users/Vooblin/starred{/owner}{/repo}",
        "contributions": 4
    },
    {
        "username": "deasuke",
        "id": 1057390,
        "followers_url": "https://api.github.com/users/deasuke/followers",
        "repositories_url": "https://api.github.com/users/deasuke/repos",
        "star_url": "https://api.github.com/users/deasuke/starred{/owner}{/repo}",
        "contributions": 4
    },
    {
        "username": "byronyi",
        "id": 2613663,
        "followers_url": "https://api.github.com/users/byronyi/followers",
        "repositories_url": "https://api.github.com/users/byronyi/repos",
        "star_url": "https://api.github.com/users/byronyi/starred{/owner}{/repo}",
        "contributions": 4
    },
    {
        "username": "2877992943",
        "id": 10953130,
        "followers_url": "https://api.github.com/users/2877992943/followers",
        "repositories_url": "https://api.github.com/users/2877992943/repos",
        "star_url": "https://api.github.com/users/2877992943/starred{/owner}{/repo}",
        "contributions": 4
    },
    {
        "username": "phamthuonghai",
        "id": 5663635,
        "followers_url": "https://api.github.com/users/phamthuonghai/followers",
        "repositories_url": "https://api.github.com/users/phamthuonghai/repos",
        "star_url": "https://api.github.com/users/phamthuonghai/starred{/owner}{/repo}",
        "contributions": 3
    },
    {
        "username": "nimaous",
        "id": 1583087,
        "followers_url": "https://api.github.com/users/nimaous/followers",
        "repositories_url": "https://api.github.com/users/nimaous/repos",
        "star_url": "https://api.github.com/users/nimaous/starred{/owner}{/repo}",
        "contributions": 3
    },
    {
        "username": "SkyAndCloud",
        "id": 12583017,
        "followers_url": "https://api.github.com/users/SkyAndCloud/followers",
        "repositories_url": "https://api.github.com/users/SkyAndCloud/repos",
        "star_url": "https://api.github.com/users/SkyAndCloud/starred{/owner}{/repo}",
        "contributions": 3
    },
    {
        "username": "kngxscn",
        "id": 4049156,
        "followers_url": "https://api.github.com/users/kngxscn/followers",
        "repositories_url": "https://api.github.com/users/kngxscn/repos",
        "star_url": "https://api.github.com/users/kngxscn/starred{/owner}{/repo}",
        "contributions": 3
    },
    {
        "username": "joaogui1",
        "id": 13261989,
        "followers_url": "https://api.github.com/users/joaogui1/followers",
        "repositories_url": "https://api.github.com/users/joaogui1/repos",
        "star_url": "https://api.github.com/users/joaogui1/starred{/owner}{/repo}",
        "contributions": 3
    },
    {
        "username": "wes-turner",
        "id": 12002965,
        "followers_url": "https://api.github.com/users/wes-turner/followers",
        "repositories_url": "https://api.github.com/users/wes-turner/repos",
        "star_url": "https://api.github.com/users/wes-turner/starred{/owner}{/repo}",
        "contributions": 3
    },
    {
        "username": "smit-hinsu",
        "id": 1990079,
        "followers_url": "https://api.github.com/users/smit-hinsu/followers",
        "repositories_url": "https://api.github.com/users/smit-hinsu/repos",
        "star_url": "https://api.github.com/users/smit-hinsu/starred{/owner}{/repo}",
        "contributions": 3
    },
    {
        "username": "0x0539",
        "id": 982999,
        "followers_url": "https://api.github.com/users/0x0539/followers",
        "repositories_url": "https://api.github.com/users/0x0539/repos",
        "star_url": "https://api.github.com/users/0x0539/starred{/owner}{/repo}",
        "contributions": 3
    },
    {
        "username": "cwbeitel",
        "id": 2348401,
        "followers_url": "https://api.github.com/users/cwbeitel/followers",
        "repositories_url": "https://api.github.com/users/cwbeitel/repos",
        "star_url": "https://api.github.com/users/cwbeitel/starred{/owner}{/repo}",
        "contributions": 3
    },
    {
        "username": "prasastoadi",
        "id": 11614678,
        "followers_url": "https://api.github.com/users/prasastoadi/followers",
        "repositories_url": "https://api.github.com/users/prasastoadi/repos",
        "star_url": "https://api.github.com/users/prasastoadi/starred{/owner}{/repo}",
        "contributions": 3
    },
    {
        "username": "k-w-w",
        "id": 31663267,
        "followers_url": "https://api.github.com/users/k-w-w/followers",
        "repositories_url": "https://api.github.com/users/k-w-w/repos",
        "star_url": "https://api.github.com/users/k-w-w/starred{/owner}{/repo}",
        "contributions": 3
    },
    {
        "username": "schani",
        "id": 61363,
        "followers_url": "https://api.github.com/users/schani/followers",
        "repositories_url": "https://api.github.com/users/schani/repos",
        "star_url": "https://api.github.com/users/schani/starred{/owner}{/repo}",
        "contributions": 3
    },
    {
        "username": "luffy06",
        "id": 7811499,
        "followers_url": "https://api.github.com/users/luffy06/followers",
        "repositories_url": "https://api.github.com/users/luffy06/repos",
        "star_url": "https://api.github.com/users/luffy06/starred{/owner}{/repo}",
        "contributions": 2
    },
    {
        "username": "Ghostvv",
        "id": 4136956,
        "followers_url": "https://api.github.com/users/Ghostvv/followers",
        "repositories_url": "https://api.github.com/users/Ghostvv/repos",
        "star_url": "https://api.github.com/users/Ghostvv/starred{/owner}{/repo}",
        "contributions": 2
    },
    {
        "username": "evcu",
        "id": 8350242,
        "followers_url": "https://api.github.com/users/evcu/followers",
        "repositories_url": "https://api.github.com/users/evcu/repos",
        "star_url": "https://api.github.com/users/evcu/starred{/owner}{/repo}",
        "contributions": 2
    },
    {
        "username": "tgale96",
        "id": 11335648,
        "followers_url": "https://api.github.com/users/tgale96/followers",
        "repositories_url": "https://api.github.com/users/tgale96/repos",
        "star_url": "https://api.github.com/users/tgale96/starred{/owner}{/repo}",
        "contributions": 2
    },
    {
        "username": "TanguyUrvoy",
        "id": 13147447,
        "followers_url": "https://api.github.com/users/TanguyUrvoy/followers",
        "repositories_url": "https://api.github.com/users/TanguyUrvoy/repos",
        "star_url": "https://api.github.com/users/TanguyUrvoy/starred{/owner}{/repo}",
        "contributions": 2
    },
    {
        "username": "syzymon",
        "id": 44476995,
        "followers_url": "https://api.github.com/users/syzymon/followers",
        "repositories_url": "https://api.github.com/users/syzymon/repos",
        "star_url": "https://api.github.com/users/syzymon/starred{/owner}{/repo}",
        "contributions": 2
    },
    {
        "username": "soaxelbrooke",
        "id": 2815794,
        "followers_url": "https://api.github.com/users/soaxelbrooke/followers",
        "repositories_url": "https://api.github.com/users/soaxelbrooke/repos",
        "star_url": "https://api.github.com/users/soaxelbrooke/starred{/owner}{/repo}",
        "contributions": 2
    },
    {
        "username": "souramoo",
        "id": 11202149,
        "followers_url": "https://api.github.com/users/souramoo/followers",
        "repositories_url": "https://api.github.com/users/souramoo/repos",
        "star_url": "https://api.github.com/users/souramoo/starred{/owner}{/repo}",
        "contributions": 2
    },
    {
        "username": "funtion",
        "id": 3072834,
        "followers_url": "https://api.github.com/users/funtion/followers",
        "repositories_url": "https://api.github.com/users/funtion/repos",
        "star_url": "https://api.github.com/users/funtion/starred{/owner}{/repo}",
        "contributions": 2
    },
    {
        "username": "cshanbo",
        "id": 9649941,
        "followers_url": "https://api.github.com/users/cshanbo/followers",
        "repositories_url": "https://api.github.com/users/cshanbo/repos",
        "star_url": "https://api.github.com/users/cshanbo/starred{/owner}{/repo}",
        "contributions": 2
    },
    {
        "username": "superbobry",
        "id": 185856,
        "followers_url": "https://api.github.com/users/superbobry/followers",
        "repositories_url": "https://api.github.com/users/superbobry/repos",
        "star_url": "https://api.github.com/users/superbobry/starred{/owner}{/repo}",
        "contributions": 2
    },
    {
        "username": "rmccorm4",
        "id": 21284872,
        "followers_url": "https://api.github.com/users/rmccorm4/followers",
        "repositories_url": "https://api.github.com/users/rmccorm4/repos",
        "star_url": "https://api.github.com/users/rmccorm4/starred{/owner}{/repo}",
        "contributions": 2
    },
    {
        "username": "theorm",
        "id": 89853,
        "followers_url": "https://api.github.com/users/theorm/followers",
        "repositories_url": "https://api.github.com/users/theorm/repos",
        "star_url": "https://api.github.com/users/theorm/starred{/owner}{/repo}",
        "contributions": 2
    },
    {
        "username": "cuixiaom",
        "id": 29615281,
        "followers_url": "https://api.github.com/users/cuixiaom/followers",
        "repositories_url": "https://api.github.com/users/cuixiaom/repos",
        "star_url": "https://api.github.com/users/cuixiaom/starred{/owner}{/repo}",
        "contributions": 2
    },
    {
        "username": "xu-song",
        "id": 13825126,
        "followers_url": "https://api.github.com/users/xu-song/followers",
        "repositories_url": "https://api.github.com/users/xu-song/repos",
        "star_url": "https://api.github.com/users/xu-song/starred{/owner}{/repo}",
        "contributions": 2
    },
    {
        "username": "wangcho2k",
        "id": 29397624,
        "followers_url": "https://api.github.com/users/wangcho2k/followers",
        "repositories_url": "https://api.github.com/users/wangcho2k/repos",
        "star_url": "https://api.github.com/users/wangcho2k/starred{/owner}{/repo}",
        "contributions": 2
    },
    {
        "username": "Michaelvll",
        "id": 6753189,
        "followers_url": "https://api.github.com/users/Michaelvll/followers",
        "repositories_url": "https://api.github.com/users/Michaelvll/repos",
        "star_url": "https://api.github.com/users/Michaelvll/starred{/owner}{/repo}",
        "contributions": 2
    },
    {
        "username": "dong-s",
        "id": 14340719,
        "followers_url": "https://api.github.com/users/dong-s/followers",
        "repositories_url": "https://api.github.com/users/dong-s/repos",
        "star_url": "https://api.github.com/users/dong-s/starred{/owner}{/repo}",
        "contributions": 2
    },
    {
        "username": "real-brilliant",
        "id": 24716125,
        "followers_url": "https://api.github.com/users/real-brilliant/followers",
        "repositories_url": "https://api.github.com/users/real-brilliant/repos",
        "star_url": "https://api.github.com/users/real-brilliant/starred{/owner}{/repo}",
        "contributions": 2
    },
    {
        "username": "haukurb",
        "id": 9802799,
        "followers_url": "https://api.github.com/users/haukurb/followers",
        "repositories_url": "https://api.github.com/users/haukurb/repos",
        "star_url": "https://api.github.com/users/haukurb/starred{/owner}{/repo}",
        "contributions": 2
    },
    {
        "username": "hsm207",
        "id": 2398765,
        "followers_url": "https://api.github.com/users/hsm207/followers",
        "repositories_url": "https://api.github.com/users/hsm207/repos",
        "star_url": "https://api.github.com/users/hsm207/starred{/owner}{/repo}",
        "contributions": 2
    },
    {
        "username": "iislucas",
        "id": 415450,
        "followers_url": "https://api.github.com/users/iislucas/followers",
        "repositories_url": "https://api.github.com/users/iislucas/repos",
        "star_url": "https://api.github.com/users/iislucas/starred{/owner}{/repo}",
        "contributions": 2
    },
    {
        "username": "jjtan",
        "id": 1111780,
        "followers_url": "https://api.github.com/users/jjtan/followers",
        "repositories_url": "https://api.github.com/users/jjtan/repos",
        "star_url": "https://api.github.com/users/jjtan/starred{/owner}{/repo}",
        "contributions": 2
    },
    {
        "username": "ksboy",
        "id": 16255580,
        "followers_url": "https://api.github.com/users/ksboy/followers",
        "repositories_url": "https://api.github.com/users/ksboy/repos",
        "star_url": "https://api.github.com/users/ksboy/starred{/owner}{/repo}",
        "contributions": 2
    },
    {
        "username": "me-sh",
        "id": 29964169,
        "followers_url": "https://api.github.com/users/me-sh/followers",
        "repositories_url": "https://api.github.com/users/me-sh/repos",
        "star_url": "https://api.github.com/users/me-sh/starred{/owner}{/repo}",
        "contributions": 2
    },
    {
        "username": "przemb",
        "id": 9627490,
        "followers_url": "https://api.github.com/users/przemb/followers",
        "repositories_url": "https://api.github.com/users/przemb/repos",
        "star_url": "https://api.github.com/users/przemb/starred{/owner}{/repo}",
        "contributions": 2
    },
    {
        "username": "kyoheikoyama",
        "id": 13311278,
        "followers_url": "https://api.github.com/users/kyoheikoyama/followers",
        "repositories_url": "https://api.github.com/users/kyoheikoyama/repos",
        "star_url": "https://api.github.com/users/kyoheikoyama/starred{/owner}{/repo}",
        "contributions": 2
    },
    {
        "username": "bwilbertz",
        "id": 14258976,
        "followers_url": "https://api.github.com/users/bwilbertz/followers",
        "repositories_url": "https://api.github.com/users/bwilbertz/repos",
        "star_url": "https://api.github.com/users/bwilbertz/starred{/owner}{/repo}",
        "contributions": 2
    },
    {
        "username": "qixiuai",
        "id": 37470231,
        "followers_url": "https://api.github.com/users/qixiuai/followers",
        "repositories_url": "https://api.github.com/users/qixiuai/repos",
        "star_url": "https://api.github.com/users/qixiuai/starred{/owner}{/repo}",
        "contributions": 2
    },
    {
        "username": "AgoloCuongHoang",
        "id": 38926056,
        "followers_url": "https://api.github.com/users/AgoloCuongHoang/followers",
        "repositories_url": "https://api.github.com/users/AgoloCuongHoang/repos",
        "star_url": "https://api.github.com/users/AgoloCuongHoang/starred{/owner}{/repo}",
        "contributions": 2
    },
    {
        "username": "Drunkar",
        "id": 1223433,
        "followers_url": "https://api.github.com/users/Drunkar/followers",
        "repositories_url": "https://api.github.com/users/Drunkar/repos",
        "star_url": "https://api.github.com/users/Drunkar/starred{/owner}{/repo}",
        "contributions": 2
    },
    {
        "username": "allenlavoie",
        "id": 3731025,
        "followers_url": "https://api.github.com/users/allenlavoie/followers",
        "repositories_url": "https://api.github.com/users/allenlavoie/repos",
        "star_url": "https://api.github.com/users/allenlavoie/starred{/owner}{/repo}",
        "contributions": 2
    },
    {
        "username": "blakehechtman",
        "id": 5957321,
        "followers_url": "https://api.github.com/users/blakehechtman/followers",
        "repositories_url": "https://api.github.com/users/blakehechtman/repos",
        "star_url": "https://api.github.com/users/blakehechtman/starred{/owner}{/repo}",
        "contributions": 2
    },
    {
        "username": "twilightdema",
        "id": 11656659,
        "followers_url": "https://api.github.com/users/twilightdema/followers",
        "repositories_url": "https://api.github.com/users/twilightdema/repos",
        "star_url": "https://api.github.com/users/twilightdema/starred{/owner}{/repo}",
        "contributions": 2
    },
    {
        "username": "davidmrau",
        "id": 20661461,
        "followers_url": "https://api.github.com/users/davidmrau/followers",
        "repositories_url": "https://api.github.com/users/davidmrau/repos",
        "star_url": "https://api.github.com/users/davidmrau/starred{/owner}{/repo}",
        "contributions": 2
    },
    {
        "username": "mrry",
        "id": 192142,
        "followers_url": "https://api.github.com/users/mrry/followers",
        "repositories_url": "https://api.github.com/users/mrry/repos",
        "star_url": "https://api.github.com/users/mrry/starred{/owner}{/repo}",
        "contributions": 2
    },
    {
        "username": "epurdy",
        "id": 923672,
        "followers_url": "https://api.github.com/users/epurdy/followers",
        "repositories_url": "https://api.github.com/users/epurdy/repos",
        "star_url": "https://api.github.com/users/epurdy/starred{/owner}{/repo}",
        "contributions": 2
    },
    {
        "username": "epurdyf",
        "id": 32338500,
        "followers_url": "https://api.github.com/users/epurdyf/followers",
        "repositories_url": "https://api.github.com/users/epurdyf/repos",
        "star_url": "https://api.github.com/users/epurdyf/starred{/owner}{/repo}",
        "contributions": 2
    },
    {
        "username": "ghego",
        "id": 837725,
        "followers_url": "https://api.github.com/users/ghego/followers",
        "repositories_url": "https://api.github.com/users/ghego/repos",
        "star_url": "https://api.github.com/users/ghego/starred{/owner}{/repo}",
        "contributions": 2
    },
    {
        "username": "gabegrand",
        "id": 10052880,
        "followers_url": "https://api.github.com/users/gabegrand/followers",
        "repositories_url": "https://api.github.com/users/gabegrand/repos",
        "star_url": "https://api.github.com/users/gabegrand/starred{/owner}{/repo}",
        "contributions": 2
    },
    {
        "username": "jaingaurav",
        "id": 84372,
        "followers_url": "https://api.github.com/users/jaingaurav/followers",
        "repositories_url": "https://api.github.com/users/jaingaurav/repos",
        "star_url": "https://api.github.com/users/jaingaurav/starred{/owner}{/repo}",
        "contributions": 2
    },
    {
        "username": "voluntadpear",
        "id": 10501948,
        "followers_url": "https://api.github.com/users/voluntadpear/followers",
        "repositories_url": "https://api.github.com/users/voluntadpear/repos",
        "star_url": "https://api.github.com/users/voluntadpear/starred{/owner}{/repo}",
        "contributions": 2
    },
    {
        "username": "Hamza5",
        "id": 7011111,
        "followers_url": "https://api.github.com/users/Hamza5/followers",
        "repositories_url": "https://api.github.com/users/Hamza5/repos",
        "star_url": "https://api.github.com/users/Hamza5/starred{/owner}{/repo}",
        "contributions": 2
    },
    {
        "username": "harini-kannan",
        "id": 3292449,
        "followers_url": "https://api.github.com/users/harini-kannan/followers",
        "repositories_url": "https://api.github.com/users/harini-kannan/repos",
        "star_url": "https://api.github.com/users/harini-kannan/starred{/owner}{/repo}",
        "contributions": 2
    },
    {
        "username": "ricsinaruto",
        "id": 18282017,
        "followers_url": "https://api.github.com/users/ricsinaruto/followers",
        "repositories_url": "https://api.github.com/users/ricsinaruto/repos",
        "star_url": "https://api.github.com/users/ricsinaruto/starred{/owner}{/repo}",
        "contributions": 2
    },
    {
        "username": "pierrot0",
        "id": 44470530,
        "followers_url": "https://api.github.com/users/pierrot0/followers",
        "repositories_url": "https://api.github.com/users/pierrot0/repos",
        "star_url": "https://api.github.com/users/pierrot0/starred{/owner}{/repo}",
        "contributions": 2
    },
    {
        "username": "psc-g",
        "id": 20324657,
        "followers_url": "https://api.github.com/users/psc-g/followers",
        "repositories_url": "https://api.github.com/users/psc-g/repos",
        "star_url": "https://api.github.com/users/psc-g/starred{/owner}{/repo}",
        "contributions": 2
    },
    {
        "username": "mirkobronzi",
        "id": 7871968,
        "followers_url": "https://api.github.com/users/mirkobronzi/followers",
        "repositories_url": "https://api.github.com/users/mirkobronzi/repos",
        "star_url": "https://api.github.com/users/mirkobronzi/starred{/owner}{/repo}",
        "contributions": 2
    },
    {
        "username": "mkroutikov",
        "id": 14280777,
        "followers_url": "https://api.github.com/users/mkroutikov/followers",
        "repositories_url": "https://api.github.com/users/mkroutikov/repos",
        "star_url": "https://api.github.com/users/mkroutikov/starred{/owner}{/repo}",
        "contributions": 2
    },
    {
        "username": "Mehrad0711",
        "id": 28717374,
        "followers_url": "https://api.github.com/users/Mehrad0711/followers",
        "repositories_url": "https://api.github.com/users/Mehrad0711/repos",
        "star_url": "https://api.github.com/users/Mehrad0711/starred{/owner}{/repo}",
        "contributions": 2
    },
    {
        "username": "MaxSobolMark",
        "id": 7015390,
        "followers_url": "https://api.github.com/users/MaxSobolMark/followers",
        "repositories_url": "https://api.github.com/users/MaxSobolMark/repos",
        "star_url": "https://api.github.com/users/MaxSobolMark/starred{/owner}{/repo}",
        "contributions": 2
    },
    {
        "username": "MarkDaoust",
        "id": 1414837,
        "followers_url": "https://api.github.com/users/MarkDaoust/followers",
        "repositories_url": "https://api.github.com/users/MarkDaoust/repos",
        "star_url": "https://api.github.com/users/MarkDaoust/starred{/owner}{/repo}",
        "contributions": 2
    },
    {
        "username": "googlehjx",
        "id": 4720688,
        "followers_url": "https://api.github.com/users/googlehjx/followers",
        "repositories_url": "https://api.github.com/users/googlehjx/repos",
        "star_url": "https://api.github.com/users/googlehjx/starred{/owner}{/repo}",
        "contributions": 2
    },
    {
        "username": "jburnim",
        "id": 347375,
        "followers_url": "https://api.github.com/users/jburnim/followers",
        "repositories_url": "https://api.github.com/users/jburnim/repos",
        "star_url": "https://api.github.com/users/jburnim/starred{/owner}{/repo}",
        "contributions": 2
    },
    {
        "username": "thominj",
        "id": 3819908,
        "followers_url": "https://api.github.com/users/thominj/followers",
        "repositories_url": "https://api.github.com/users/thominj/repos",
        "star_url": "https://api.github.com/users/thominj/starred{/owner}{/repo}",
        "contributions": 2
    },
    {
        "username": "WuTheFWasThat",
        "id": 1479648,
        "followers_url": "https://api.github.com/users/WuTheFWasThat/followers",
        "repositories_url": "https://api.github.com/users/WuTheFWasThat/repos",
        "star_url": "https://api.github.com/users/WuTheFWasThat/starred{/owner}{/repo}",
        "contributions": 2
    },
    {
        "username": "twairball",
        "id": 1191601,
        "followers_url": "https://api.github.com/users/twairball/followers",
        "repositories_url": "https://api.github.com/users/twairball/repos",
        "star_url": "https://api.github.com/users/twairball/starred{/owner}{/repo}",
        "contributions": 2
    },
    {
        "username": "martiansideofthemoon",
        "id": 8805240,
        "followers_url": "https://api.github.com/users/martiansideofthemoon/followers",
        "repositories_url": "https://api.github.com/users/martiansideofthemoon/repos",
        "star_url": "https://api.github.com/users/martiansideofthemoon/starred{/owner}{/repo}",
        "contributions": 2
    },
    {
        "username": "cfiken",
        "id": 1255485,
        "followers_url": "https://api.github.com/users/cfiken/followers",
        "repositories_url": "https://api.github.com/users/cfiken/repos",
        "star_url": "https://api.github.com/users/cfiken/starred{/owner}{/repo}",
        "contributions": 2
    },
    {
        "username": "lzhang10",
        "id": 1021650,
        "followers_url": "https://api.github.com/users/lzhang10/followers",
        "repositories_url": "https://api.github.com/users/lzhang10/repos",
        "star_url": "https://api.github.com/users/lzhang10/starred{/owner}{/repo}",
        "contributions": 2
    },
    {
        "username": "tjgq",
        "id": 4370077,
        "followers_url": "https://api.github.com/users/tjgq/followers",
        "repositories_url": "https://api.github.com/users/tjgq/repos",
        "star_url": "https://api.github.com/users/tjgq/starred{/owner}{/repo}",
        "contributions": 1
    },
    {
        "username": "omalleyt12",
        "id": 29100818,
        "followers_url": "https://api.github.com/users/omalleyt12/followers",
        "repositories_url": "https://api.github.com/users/omalleyt12/repos",
        "star_url": "https://api.github.com/users/omalleyt12/starred{/owner}{/repo}",
        "contributions": 1
    },
    {
        "username": "shivaniag",
        "id": 16565716,
        "followers_url": "https://api.github.com/users/shivaniag/followers",
        "repositories_url": "https://api.github.com/users/shivaniag/repos",
        "star_url": "https://api.github.com/users/shivaniag/starred{/owner}{/repo}",
        "contributions": 1
    },
    {
        "username": "sharannarang",
        "id": 7253756,
        "followers_url": "https://api.github.com/users/sharannarang/followers",
        "repositories_url": "https://api.github.com/users/sharannarang/repos",
        "star_url": "https://api.github.com/users/sharannarang/starred{/owner}{/repo}",
        "contributions": 1
    },
    {
        "username": "shahzeb1",
        "id": 1383831,
        "followers_url": "https://api.github.com/users/shahzeb1/followers",
        "repositories_url": "https://api.github.com/users/shahzeb1/repos",
        "star_url": "https://api.github.com/users/shahzeb1/starred{/owner}{/repo}",
        "contributions": 1
    },
    {
        "username": "ShahNewazKhan",
        "id": 3241700,
        "followers_url": "https://api.github.com/users/ShahNewazKhan/followers",
        "repositories_url": "https://api.github.com/users/ShahNewazKhan/repos",
        "star_url": "https://api.github.com/users/ShahNewazKhan/starred{/owner}{/repo}",
        "contributions": 1
    },
    {
        "username": "activatedgeek",
        "id": 3909933,
        "followers_url": "https://api.github.com/users/activatedgeek/followers",
        "repositories_url": "https://api.github.com/users/activatedgeek/repos",
        "star_url": "https://api.github.com/users/activatedgeek/starred{/owner}{/repo}",
        "contributions": 1
    },
    {
        "username": "santiaontanon-google",
        "id": 86324147,
        "followers_url": "https://api.github.com/users/santiaontanon-google/followers",
        "repositories_url": "https://api.github.com/users/santiaontanon-google/repos",
        "star_url": "https://api.github.com/users/santiaontanon-google/starred{/owner}{/repo}",
        "contributions": 1
    },
    {
        "username": "rsepassi",
        "id": 1115739,
        "followers_url": "https://api.github.com/users/rsepassi/followers",
        "repositories_url": "https://api.github.com/users/rsepassi/repos",
        "star_url": "https://api.github.com/users/rsepassi/starred{/owner}{/repo}",
        "contributions": 1
    },
    {
        "username": "rjpower",
        "id": 607207,
        "followers_url": "https://api.github.com/users/rjpower/followers",
        "repositories_url": "https://api.github.com/users/rjpower/repos",
        "star_url": "https://api.github.com/users/rjpower/starred{/owner}{/repo}",
        "contributions": 1
    },
    {
        "username": "rasmi",
        "id": 2267370,
        "followers_url": "https://api.github.com/users/rasmi/followers",
        "repositories_url": "https://api.github.com/users/rasmi/repos",
        "star_url": "https://api.github.com/users/rasmi/starred{/owner}{/repo}",
        "contributions": 1
    },
    {
        "username": "raphael-sch",
        "id": 11199256,
        "followers_url": "https://api.github.com/users/raphael-sch/followers",
        "repositories_url": "https://api.github.com/users/raphael-sch/repos",
        "star_url": "https://api.github.com/users/raphael-sch/starred{/owner}{/repo}",
        "contributions": 1
    },
    {
        "username": "noe",
        "id": 4972,
        "followers_url": "https://api.github.com/users/noe/followers",
        "repositories_url": "https://api.github.com/users/noe/repos",
        "star_url": "https://api.github.com/users/noe/starred{/owner}{/repo}",
        "contributions": 1
    },
    {
        "username": "normster",
        "id": 6687910,
        "followers_url": "https://api.github.com/users/normster/followers",
        "repositories_url": "https://api.github.com/users/normster/repos",
        "star_url": "https://api.github.com/users/normster/starred{/owner}{/repo}",
        "contributions": 1
    },
    {
        "username": "nfiedel",
        "id": 447896,
        "followers_url": "https://api.github.com/users/nfiedel/followers",
        "repositories_url": "https://api.github.com/users/nfiedel/repos",
        "star_url": "https://api.github.com/users/nfiedel/starred{/owner}{/repo}",
        "contributions": 1
    },
    {
        "username": "nhasabni",
        "id": 22304502,
        "followers_url": "https://api.github.com/users/nhasabni/followers",
        "repositories_url": "https://api.github.com/users/nhasabni/repos",
        "star_url": "https://api.github.com/users/nhasabni/starred{/owner}{/repo}",
        "contributions": 1
    },
    {
        "username": "NadavB",
        "id": 51364488,
        "followers_url": "https://api.github.com/users/NadavB/followers",
        "repositories_url": "https://api.github.com/users/NadavB/repos",
        "star_url": "https://api.github.com/users/NadavB/starred{/owner}{/repo}",
        "contributions": 1
    },
    {
        "username": "mts42000",
        "id": 4112440,
        "followers_url": "https://api.github.com/users/mts42000/followers",
        "repositories_url": "https://api.github.com/users/mts42000/repos",
        "star_url": "https://api.github.com/users/mts42000/starred{/owner}{/repo}",
        "contributions": 1
    },
    {
        "username": "Mistobaan",
        "id": 112599,
        "followers_url": "https://api.github.com/users/Mistobaan/followers",
        "repositories_url": "https://api.github.com/users/Mistobaan/repos",
        "star_url": "https://api.github.com/users/Mistobaan/starred{/owner}{/repo}",
        "contributions": 1
    },
    {
        "username": "vfdev-5",
        "id": 2459423,
        "followers_url": "https://api.github.com/users/vfdev-5/followers",
        "repositories_url": "https://api.github.com/users/vfdev-5/repos",
        "star_url": "https://api.github.com/users/vfdev-5/starred{/owner}{/repo}",
        "contributions": 1
    },
    {
        "username": "aman-tiwari",
        "id": 8798016,
        "followers_url": "https://api.github.com/users/aman-tiwari/followers",
        "repositories_url": "https://api.github.com/users/aman-tiwari/repos",
        "star_url": "https://api.github.com/users/aman-tiwari/starred{/owner}{/repo}",
        "contributions": 1
    },
    {
        "username": "resec",
        "id": 4277636,
        "followers_url": "https://api.github.com/users/resec/followers",
        "repositories_url": "https://api.github.com/users/resec/repos",
        "star_url": "https://api.github.com/users/resec/starred{/owner}{/repo}",
        "contributions": 1
    },
    {
        "username": "repoloper",
        "id": 41405759,
        "followers_url": "https://api.github.com/users/repoloper/followers",
        "repositories_url": "https://api.github.com/users/repoloper/repos",
        "star_url": "https://api.github.com/users/repoloper/starred{/owner}{/repo}",
        "contributions": 1
    },
    {
        "username": "lhlmgr",
        "id": 400331,
        "followers_url": "https://api.github.com/users/lhlmgr/followers",
        "repositories_url": "https://api.github.com/users/lhlmgr/repos",
        "star_url": "https://api.github.com/users/lhlmgr/starred{/owner}{/repo}",
        "contributions": 1
    },
    {
        "username": "lazylife7157",
        "id": 26483896,
        "followers_url": "https://api.github.com/users/lazylife7157/followers",
        "repositories_url": "https://api.github.com/users/lazylife7157/repos",
        "star_url": "https://api.github.com/users/lazylife7157/starred{/owner}{/repo}",
        "contributions": 1
    },
    {
        "username": "jurasofish",
        "id": 33386122,
        "followers_url": "https://api.github.com/users/jurasofish/followers",
        "repositories_url": "https://api.github.com/users/jurasofish/repos",
        "star_url": "https://api.github.com/users/jurasofish/starred{/owner}{/repo}",
        "contributions": 1
    },
    {
        "username": "jekbradbury",
        "id": 11729078,
        "followers_url": "https://api.github.com/users/jekbradbury/followers",
        "repositories_url": "https://api.github.com/users/jekbradbury/repos",
        "star_url": "https://api.github.com/users/jekbradbury/starred{/owner}{/repo}",
        "contributions": 1
    },
    {
        "username": "fstahlberg",
        "id": 16489135,
        "followers_url": "https://api.github.com/users/fstahlberg/followers",
        "repositories_url": "https://api.github.com/users/fstahlberg/repos",
        "star_url": "https://api.github.com/users/fstahlberg/starred{/owner}{/repo}",
        "contributions": 1
    },
    {
        "username": "evalphobia",
        "id": 2827521,
        "followers_url": "https://api.github.com/users/evalphobia/followers",
        "repositories_url": "https://api.github.com/users/evalphobia/repos",
        "star_url": "https://api.github.com/users/evalphobia/starred{/owner}{/repo}",
        "contributions": 1
    },
    {
        "username": "adgitate1",
        "id": 8494994,
        "followers_url": "https://api.github.com/users/adgitate1/followers",
        "repositories_url": "https://api.github.com/users/adgitate1/repos",
        "star_url": "https://api.github.com/users/adgitate1/starred{/owner}{/repo}",
        "contributions": 1
    },
    {
        "username": "zyshin",
        "id": 4653774,
        "followers_url": "https://api.github.com/users/zyshin/followers",
        "repositories_url": "https://api.github.com/users/zyshin/repos",
        "star_url": "https://api.github.com/users/zyshin/starred{/owner}{/repo}",
        "contributions": 1
    },
    {
        "username": "yilei",
        "id": 581947,
        "followers_url": "https://api.github.com/users/yilei/followers",
        "repositories_url": "https://api.github.com/users/yilei/repos",
        "star_url": "https://api.github.com/users/yilei/starred{/owner}{/repo}",
        "contributions": 1
    },
    {
        "username": "peakji",
        "id": 219051,
        "followers_url": "https://api.github.com/users/peakji/followers",
        "repositories_url": "https://api.github.com/users/peakji/repos",
        "star_url": "https://api.github.com/users/peakji/starred{/owner}{/repo}",
        "contributions": 1
    },
    {
        "username": "ywen666",
        "id": 40072408,
        "followers_url": "https://api.github.com/users/ywen666/followers",
        "repositories_url": "https://api.github.com/users/ywen666/repos",
        "star_url": "https://api.github.com/users/ywen666/starred{/owner}{/repo}",
        "contributions": 1
    },
    {
        "username": "yanboliang",
        "id": 1962026,
        "followers_url": "https://api.github.com/users/yanboliang/followers",
        "repositories_url": "https://api.github.com/users/yanboliang/repos",
        "star_url": "https://api.github.com/users/yanboliang/starred{/owner}{/repo}",
        "contributions": 1
    },
    {
        "username": "XiaoqingNLP",
        "id": 12473617,
        "followers_url": "https://api.github.com/users/XiaoqingNLP/followers",
        "repositories_url": "https://api.github.com/users/XiaoqingNLP/repos",
        "star_url": "https://api.github.com/users/XiaoqingNLP/starred{/owner}{/repo}",
        "contributions": 1
    },
    {
        "username": "wanqizhu",
        "id": 14876488,
        "followers_url": "https://api.github.com/users/wanqizhu/followers",
        "repositories_url": "https://api.github.com/users/wanqizhu/repos",
        "star_url": "https://api.github.com/users/wanqizhu/starred{/owner}{/repo}",
        "contributions": 1
    },
    {
        "username": "duyvuleo",
        "id": 5590702,
        "followers_url": "https://api.github.com/users/duyvuleo/followers",
        "repositories_url": "https://api.github.com/users/duyvuleo/repos",
        "star_url": "https://api.github.com/users/duyvuleo/starred{/owner}{/repo}",
        "contributions": 1
    },
    {
        "username": "mihaimaruseac",
        "id": 323199,
        "followers_url": "https://api.github.com/users/mihaimaruseac/followers",
        "repositories_url": "https://api.github.com/users/mihaimaruseac/repos",
        "star_url": "https://api.github.com/users/mihaimaruseac/starred{/owner}{/repo}",
        "contributions": 1
    },
    {
        "username": "fionalang",
        "id": 42980436,
        "followers_url": "https://api.github.com/users/fionalang/followers",
        "repositories_url": "https://api.github.com/users/fionalang/repos",
        "star_url": "https://api.github.com/users/fionalang/starred{/owner}{/repo}",
        "contributions": 1
    },
    {
        "username": "elmisback",
        "id": 8119219,
        "followers_url": "https://api.github.com/users/elmisback/followers",
        "repositories_url": "https://api.github.com/users/elmisback/repos",
        "star_url": "https://api.github.com/users/elmisback/starred{/owner}{/repo}",
        "contributions": 1
    },
    {
        "username": "dimitry12",
        "id": 484357,
        "followers_url": "https://api.github.com/users/dimitry12/followers",
        "repositories_url": "https://api.github.com/users/dimitry12/repos",
        "star_url": "https://api.github.com/users/dimitry12/starred{/owner}{/repo}",
        "contributions": 1
    },
    {
        "username": "gharibian",
        "id": 7423210,
        "followers_url": "https://api.github.com/users/gharibian/followers",
        "repositories_url": "https://api.github.com/users/gharibian/repos",
        "star_url": "https://api.github.com/users/gharibian/starred{/owner}{/repo}",
        "contributions": 1
    },
    {
        "username": "derekmauro",
        "id": 761129,
        "followers_url": "https://api.github.com/users/derekmauro/followers",
        "repositories_url": "https://api.github.com/users/derekmauro/repos",
        "star_url": "https://api.github.com/users/derekmauro/starred{/owner}{/repo}",
        "contributions": 1
    },
    {
        "username": "dfurrer",
        "id": 110301,
        "followers_url": "https://api.github.com/users/dfurrer/followers",
        "repositories_url": "https://api.github.com/users/dfurrer/repos",
        "star_url": "https://api.github.com/users/dfurrer/starred{/owner}{/repo}",
        "contributions": 1
    },
    {
        "username": "dan-zheng",
        "id": 5590046,
        "followers_url": "https://api.github.com/users/dan-zheng/followers",
        "repositories_url": "https://api.github.com/users/dan-zheng/repos",
        "star_url": "https://api.github.com/users/dan-zheng/starred{/owner}{/repo}",
        "contributions": 1
    },
    {
        "username": "chrisgorgo",
        "id": 238759,
        "followers_url": "https://api.github.com/users/chrisgorgo/followers",
        "repositories_url": "https://api.github.com/users/chrisgorgo/repos",
        "star_url": "https://api.github.com/users/chrisgorgo/starred{/owner}{/repo}",
        "contributions": 1
    },
    {
        "username": "changlan",
        "id": 603293,
        "followers_url": "https://api.github.com/users/changlan/followers",
        "repositories_url": "https://api.github.com/users/changlan/repos",
        "star_url": "https://api.github.com/users/changlan/starred{/owner}{/repo}",
        "contributions": 1
    },
    {
        "username": "brianwa84",
        "id": 22173987,
        "followers_url": "https://api.github.com/users/brianwa84/followers",
        "repositories_url": "https://api.github.com/users/brianwa84/repos",
        "star_url": "https://api.github.com/users/brianwa84/starred{/owner}{/repo}",
        "contributions": 1
    },
    {
        "username": "balbertalli",
        "id": 3444375,
        "followers_url": "https://api.github.com/users/balbertalli/followers",
        "repositories_url": "https://api.github.com/users/balbertalli/repos",
        "star_url": "https://api.github.com/users/balbertalli/starred{/owner}{/repo}",
        "contributions": 1
    },
    {
        "username": "brettkoonce",
        "id": 11281814,
        "followers_url": "https://api.github.com/users/brettkoonce/followers",
        "repositories_url": "https://api.github.com/users/brettkoonce/repos",
        "star_url": "https://api.github.com/users/brettkoonce/starred{/owner}{/repo}",
        "contributions": 1
    },
    {
        "username": "bwindsor22",
        "id": 25360076,
        "followers_url": "https://api.github.com/users/bwindsor22/followers",
        "repositories_url": "https://api.github.com/users/bwindsor22/repos",
        "star_url": "https://api.github.com/users/bwindsor22/starred{/owner}{/repo}",
        "contributions": 1
    },
    {
        "username": "d0k",
        "id": 16542,
        "followers_url": "https://api.github.com/users/d0k/followers",
        "repositories_url": "https://api.github.com/users/d0k/repos",
        "star_url": "https://api.github.com/users/d0k/starred{/owner}{/repo}",
        "contributions": 1
    },
    {
        "username": "bloops",
        "id": 893412,
        "followers_url": "https://api.github.com/users/bloops/followers",
        "repositories_url": "https://api.github.com/users/bloops/repos",
        "star_url": "https://api.github.com/users/bloops/starred{/owner}{/repo}",
        "contributions": 1
    },
    {
        "username": "andrewluchen",
        "id": 6128079,
        "followers_url": "https://api.github.com/users/andrewluchen/followers",
        "repositories_url": "https://api.github.com/users/andrewluchen/repos",
        "star_url": "https://api.github.com/users/andrewluchen/starred{/owner}{/repo}",
        "contributions": 1
    },
    {
        "username": "albertz",
        "id": 59132,
        "followers_url": "https://api.github.com/users/albertz/followers",
        "repositories_url": "https://api.github.com/users/albertz/repos",
        "star_url": "https://api.github.com/users/albertz/starred{/owner}{/repo}",
        "contributions": 1
    },
    {
        "username": "adarob",
        "id": 1088232,
        "followers_url": "https://api.github.com/users/adarob/followers",
        "repositories_url": "https://api.github.com/users/adarob/repos",
        "star_url": "https://api.github.com/users/adarob/starred{/owner}{/repo}",
        "contributions": 1
    },
    {
        "username": "ajbouh",
        "id": 7325,
        "followers_url": "https://api.github.com/users/ajbouh/followers",
        "repositories_url": "https://api.github.com/users/ajbouh/repos",
        "star_url": "https://api.github.com/users/ajbouh/starred{/owner}{/repo}",
        "contributions": 1
    },
    {
        "username": "mschonwe",
        "id": 101855,
        "followers_url": "https://api.github.com/users/mschonwe/followers",
        "repositories_url": "https://api.github.com/users/mschonwe/repos",
        "star_url": "https://api.github.com/users/mschonwe/starred{/owner}{/repo}",
        "contributions": 1
    },
    {
        "username": "mzilinec",
        "id": 29761822,
        "followers_url": "https://api.github.com/users/mzilinec/followers",
        "repositories_url": "https://api.github.com/users/mzilinec/repos",
        "star_url": "https://api.github.com/users/mzilinec/starred{/owner}{/repo}",
        "contributions": 1
    },
    {
        "username": "marcvanzee",
        "id": 180100,
        "followers_url": "https://api.github.com/users/marcvanzee/followers",
        "repositories_url": "https://api.github.com/users/marcvanzee/repos",
        "star_url": "https://api.github.com/users/marcvanzee/starred{/owner}{/repo}",
        "contributions": 1
    },
    {
        "username": "lucienwang1009",
        "id": 28888626,
        "followers_url": "https://api.github.com/users/lucienwang1009/followers",
        "repositories_url": "https://api.github.com/users/lucienwang1009/repos",
        "star_url": "https://api.github.com/users/lucienwang1009/starred{/owner}{/repo}",
        "contributions": 1
    },
    {
        "username": "kayzhu",
        "id": 1530877,
        "followers_url": "https://api.github.com/users/kayzhu/followers",
        "repositories_url": "https://api.github.com/users/kayzhu/repos",
        "star_url": "https://api.github.com/users/kayzhu/starred{/owner}{/repo}",
        "contributions": 1
    },
    {
        "username": "jvdillon",
        "id": 1137078,
        "followers_url": "https://api.github.com/users/jvdillon/followers",
        "repositories_url": "https://api.github.com/users/jvdillon/repos",
        "star_url": "https://api.github.com/users/jvdillon/starred{/owner}{/repo}",
        "contributions": 1
    },
    {
        "username": "jarfo",
        "id": 1847186,
        "followers_url": "https://api.github.com/users/jarfo/followers",
        "repositories_url": "https://api.github.com/users/jarfo/repos",
        "star_url": "https://api.github.com/users/jarfo/starred{/owner}{/repo}",
        "contributions": 1
    },
    {
        "username": "y0ast",
        "id": 485778,
        "followers_url": "https://api.github.com/users/y0ast/followers",
        "repositories_url": "https://api.github.com/users/y0ast/repos",
        "star_url": "https://api.github.com/users/y0ast/starred{/owner}{/repo}",
        "contributions": 1
    },
    {
        "username": "j2i2",
        "id": 67613793,
        "followers_url": "https://api.github.com/users/j2i2/followers",
        "repositories_url": "https://api.github.com/users/j2i2/repos",
        "star_url": "https://api.github.com/users/j2i2/starred{/owner}{/repo}",
        "contributions": 1
    },
    {
        "username": "johnglover",
        "id": 343435,
        "followers_url": "https://api.github.com/users/johnglover/followers",
        "repositories_url": "https://api.github.com/users/johnglover/repos",
        "star_url": "https://api.github.com/users/johnglover/starred{/owner}{/repo}",
        "contributions": 1
    },
    {
        "username": "joel-shor",
        "id": 6020988,
        "followers_url": "https://api.github.com/users/joel-shor/followers",
        "repositories_url": "https://api.github.com/users/joel-shor/repos",
        "star_url": "https://api.github.com/users/joel-shor/starred{/owner}{/repo}",
        "contributions": 1
    },
    {
        "username": "jblespiau",
        "id": 534945,
        "followers_url": "https://api.github.com/users/jblespiau/followers",
        "repositories_url": "https://api.github.com/users/jblespiau/repos",
        "star_url": "https://api.github.com/users/jblespiau/starred{/owner}{/repo}",
        "contributions": 1
    },
    {
        "username": "james-martens",
        "id": 8484861,
        "followers_url": "https://api.github.com/users/james-martens/followers",
        "repositories_url": "https://api.github.com/users/james-martens/repos",
        "star_url": "https://api.github.com/users/james-martens/starred{/owner}{/repo}",
        "contributions": 1
    },
    {
        "username": "jaywalnut310",
        "id": 20279210,
        "followers_url": "https://api.github.com/users/jaywalnut310/followers",
        "repositories_url": "https://api.github.com/users/jaywalnut310/repos",
        "star_url": "https://api.github.com/users/jaywalnut310/starred{/owner}{/repo}",
        "contributions": 1
    },
    {
        "username": "ip01",
        "id": 1575739,
        "followers_url": "https://api.github.com/users/ip01/followers",
        "repositories_url": "https://api.github.com/users/ip01/repos",
        "star_url": "https://api.github.com/users/ip01/starred{/owner}{/repo}",
        "contributions": 1
    },
    {
        "username": "iansimon",
        "id": 1361775,
        "followers_url": "https://api.github.com/users/iansimon/followers",
        "repositories_url": "https://api.github.com/users/iansimon/repos",
        "star_url": "https://api.github.com/users/iansimon/starred{/owner}{/repo}",
        "contributions": 1
    },
    {
        "username": "hsudhof",
        "id": 22355231,
        "followers_url": "https://api.github.com/users/hsudhof/followers",
        "repositories_url": "https://api.github.com/users/hsudhof/repos",
        "star_url": "https://api.github.com/users/hsudhof/starred{/owner}{/repo}",
        "contributions": 1
    },
    {
        "username": "GuiyuDu",
        "id": 6398751,
        "followers_url": "https://api.github.com/users/GuiyuDu/followers",
        "repositories_url": "https://api.github.com/users/GuiyuDu/repos",
        "star_url": "https://api.github.com/users/GuiyuDu/starred{/owner}{/repo}",
        "contributions": 1
    },
    {
        "username": "w-hat",
        "id": 21134804,
        "followers_url": "https://api.github.com/users/w-hat/followers",
        "repositories_url": "https://api.github.com/users/w-hat/repos",
        "star_url": "https://api.github.com/users/w-hat/starred{/owner}{/repo}",
        "contributions": 1
    }
]